DatastreamUCS/DSConnect.py
DatastreamUCS/DSUserDataObjectBase.py
DatastreamUCS/DS_Requests.py
DatastreamUCS/DS_Response.py
DatastreamUCS/DatastreamEconomicFilters.py
DatastreamUCS/DatastreamUserCreated_TimeSeries.py
DatastreamUCS/__init__.py
DatastreamUCS-1.0.19.dist-info/METADATA
DatastreamUCS-1.0.19.dist-info/WHEEL
DatastreamUCS-1.0.19.dist-info/top_level.txt
DatastreamUCS-1.0.19.dist-info/RECORD
